{
  "url": "https://www.computerscience.org/careers/",
  "title": "Top Careers in Computer Science | Careers, Salaries, and Resources",
  "extracted_data": {
    "title": "Top Careers in Computer Science | Careers, Salaries, and Resources",
    "main_content": "![](https://res.cloudinary.com/highereducation/images/f_auto,q_auto/g_face,c_fill,fl_lossy,q_auto:best,w_448,h_382/v1662131233/ComputerScience.org/CompSci_Careers_FTR_2969cf52f/CompSci_Careers_FTR_2969cf52f.jpg?_i=AA)\nTypical duties for workers with information technology (IT) and computer science jobs include developing and supporting computer systems, networks, software, and hardware. High-employing industries for computer science professionals include software publishing, higher education, government agencies, and computer systems design.\nSome of the highest-paying and most in-demand computer science roles include software developer, computer and information research scientist, and information security analyst.\nMany entry-level jobs in this field require at least a bachelor's degree. Depending on your specific career goal, you may also need a master's degree. However, professionals can also land positions without a computer science degree if they complete a coding bootcamp, teach themselves key skills, or earn relevant computer science professional certifications.\nUse our guide to learn more about some of the best careers in computer science, including the different computer science fields of work and how to find a job in this growing space. We describe what to expect from computer science jobs, highlight several prominent employers, and provide helpful resources.\nPopular Online Programs\nLearn about start dates, transferring credits, availability of financial aid, and more by contacting the universities below.\nTop Five Computer Science Jobs by Salary\nComputer Science Career | Median Annual Salary, May 2023 |\n---|---|\n|\n[$145,080](https://www.bls.gov/oes/current/oes151221.htm)[Software Developers](/careers/software-developer/)\n[$132,270](https://www.bls.gov/oes/current/oes151252.htm)[$129,840](https://www.bls.gov/oes/current/oes151241.htm)[Information Security Analysts](/careers/information-security-analyst/)\n[$120,360](https://www.bls.gov/oes/current/oes151212.htm)[Database Administrators](/careers/database-administrator/)\n[$101,510](https://www.bls.gov/oes/current/oes151242.htm)[BLS](https://www.bls.gov/oes/current/oes_stru.htm)\nTop Five Computer Science Jobs by Outlook\nComputer Science Career | Job Outlook, 2022-32 |\n---|---|\nInformation Security Analysts |\n|\n[+25%](https://www.bls.gov/ooh/computer-and-information-technology/software-developers.htm)[+23%](https://www.bls.gov/ooh/computer-and-information-technology/computer-and-information-research-scientists.htm)[Web Developers](/careers/web-developer/)and Digital Designers\n[+16%](https://www.bls.gov/ooh/computer-and-information-technology/web-developers.htm)[Computer Systems Analysts](/careers/systems-analyst/)\n[+10%](https://www.bls.gov/ooh/computer-and-information-technology/computer-systems-analysts.htm)[BLS](https://www.bls.gov/ooh/)\nSalary Potential and Career Outlook for Computer Scientists\nThe [U.S. Bureau of Labor Statistics](https://www.bls.gov/ooh/computer-and-information-technology/home.htm) (BLS) projects 23% growth for computer science and information technology jobs between 2022 and 2032 — a much-faster-than-average growth rate, which may indicate continued demand for workers with tech skills as society continues to incorporate technology into everyday life.\n[BLS data](https://www.bls.gov/oes/current/oes151299.htm) also reveals computer science and related occupations earn higher-than-average wages: Their median annual salary was $104,920 in May 2023, more than double the median wage of $45,760 for all workers nationwide.\nExplore the two charts below for data about some of the highest-paid and fastest-growing [computer science jobs](/resources/best-computer-science-jobs/).\nMajor Employers of Computer Scientists\n-\nMicrosoft: Founded in 1975 and headquartered in Redmond, Washington, Microsoft is the largest software maker globally. The company employs 221,000 workers worldwide, including 120,000 in the U.S. Microsoft hires tech professionals in roles like software engineer, data scientist, and solution architect. -\nAlphabet: Alphabet is the parent company of Google, one of the world's biggest internet product creators and suppliers. To advance its mission to \"organize the world's information and make it universally accessible and useful,\" Google employs various computer science professionals, including software engineers, UX researchers, and software developers. -\nApple: The company behind the iPhone and Mac computers, Apple is a global juggernaut, reporting a quarterly revenue of $119.6 billion in February 2024. Apple offers computer science jobs in hardware, software and services, and machine learning and AI. -\nAmazon: In addition to online shopping, Amazon offers cloud services, hardware devices, entertainment, and delivery and logistics. Computer science professionals can find jobs in software development, software engineering, and data science at Amazon. -\nMeta: Originally created in 2004 under the name Facebook, Meta is a tech company that runs social media and communication platforms. They are also developing augmented and virtual reality tools for social experiences. Meta hires computer science professionals for roles like computer research scientist, security software engineer, product designer, and data scientist. -\nU.S. Department of Defense: The largest government agency in the U.S., the Department of Defense (DoD), deploys military personnel to help deter war and advance national security. The department develops quick, agile, advanced technology to protect American lives and interests. DoD jobs for people with computer science degrees include cyberthreat analysts, machine learning scientists, and artificial intelligence engineers. -\nNIKE, Inc: Globally recognized for its bestselling Nike, Jordan, and Converse brands, NIKE produces top-selling athletic shoes and apparel. The company uses technology to develop products, support design engineers, and harness big data from around the world. Its technology team includes lead Android engineers, cyberdefense analysts, and technical operations specialists.\nNote this list is not exhaustive. Other large companies that hire tech workers include Intel, IBM, and Cisco, and many other smaller organizations also employ computer and IT professionals.\nFind Your Computer Science Career\n[Computer Engineer](https://www.computerscience.org/computer-engineering/careers/computer-engineer/)[Computer Forensics Investigator](https://www.computerscience.org/careers/computer-forensics-investigator/)[Computer Programmer](https://www.computerscience.org/careers/computer-programmer/)[Data Scientist](https://www.computerscience.org/careers/data-science/)[Database Administrator](https://www.computerscience.org/careers/database-administrator/)[Full-Stack Developer](https://www.computerscience.org/web-development/careers/full-stack-developer/)[Hardware Engineer](https://www.computerscience.org/careers/computer-hardware-engineer/)[Health Information Technician](https://www.computerscience.org/careers/health-information-technician/)[Information Researcher](https://www.computerscience.org/careers/computer-information-researcher/)[Information Security Analyst](https://www.computerscience.org/careers/information-security-analyst/)[Information Technology Architect](https://www.computerscience.org/careers/information-technology-architect/)[Network Administrator](https://www.computerscience.org/careers/network-administrator/)[Software Developer](https://www.computerscience.org/careers/software-developer/)[Software Engineer](https://www.computerscience.org/careers/software-engineer/)[Systems Analyst](https://www.computerscience.org/careers/systems-analyst/)[Systems Manager](https://www.computerscience.org/careers/systems-manager/)[Video Game Designer](https://www.computerscience.org/careers/video-game-designer/)[Web Designer](https://www.computerscience.org/careers/web-design/)[Web Developer](https://www.computerscience.org/careers/web-developer/)\nPopular Online Programs\nLearn about start dates, transferring credits, availability of financial aid, and more by contacting the universities below.\nGet a Tech Job With a Computer Science Degree\nMany careers in computer science — like software developer, information security analyst, and database administrator — typically require a bachelor's [degree in computer science](/degrees/). Entry-level roles for most positions in this field do not require relevant work experience, though completing an internship or maintaining a programming portfolio can help you stand out in the job search.\nSome computer science roles, such as computer and information research scientist, require a master's degree. Even if employers do not require a graduate degree, holding an advanced educational credential can help you qualify for upper-level jobs and higher salaries. Some companies may even cover master's program tuition as part of their [education benefits](/resources/companies-that-pay-for-college/).\nIn some cases, you can qualify for entry-level tech positions after completing a [computer science bootcamp](/bootcamps/resources/bootcamps-vs-degrees/) and/or earning [computer science certifications](/degrees/certifications/computer-science/). Learn about some of the [leading tech companies](/resources/companies-that-dont-require-a-college-degree/) where you can work without earning a computer science degree.\nDiscover Resources for Working in Computer Science\nProfessional organizations can help computer science students and career switchers network, find work opportunities, and stay updated on new developments in the field. In addition to the options below, you can join organizations like the [IAENG Society of Software Engineering](https://www.iaeng.org/ISSE.html) or [computer science Meetup groups](https://www.meetup.com/topics/computer-science/).\nHelp for Computer Science Students\n[Association for Computing Machinery](https://www.acm.org/)\nThe largest computing society in the world, ACM includes 38 special interest groups and 860 local chapters. Members can access publications, conferences, and networking opportunities.\n[Computing Research Association](https://cra.org/)\nCRA includes 250 member organizations from North America that work on computing research problems. Founded in 1972, the group includes government, research, and academic members.\n[IEEE Computer Society](https://www.computer.org/)\nThis organization helps computer science and engineering professionals in all areas of the field advance in their careers through webinars, conferences, and publications.\n[Association for Women in Computing](https://www.awc-hq.org/home.html)\nBased in Washington, DC, AWC provides members mentoring, education, service, and networking opportunities through local chapters nationwide.\nHelp for Career Switchers\n[CompTIA Career Change](https://www.comptia.org/career-change)\nCompTIA offers professional tech certifications and training to help you launch or advance your computer science career.\n[Learn to Code with Me](https://learntocodewith.me/posts/career-change-at-40/)\nThis organization offers advice for learning computer science and shifting into tech careers.\n[edX](https://www.edx.org/)\nAn online learning platform, edX offers free or affordable courses, certificates, and micro-master's programs in various tech-related fields.\n[InfoSec Institute](https://www.infosecinstitute.com/)\nThis organization provides technical training, certifications, and self-paced learning programs to prepare people without computer science degrees for tech jobs.\nFAQ About Computer Science Degrees and Jobs\nDo you need a computer science degree to get a job in tech?\nIf you earn a computer science degree, you can qualify for an array of entry-level tech jobs like computer programmer, software developer, and database administrator. However, you may also land tech roles without a degree by completing a bootcamp, earning a professional certification, or building a portfolio that highlights your relevant knowledge and skills.\nWhat jobs can you get with a computer science degree?\nWhich tech careers you qualify for depends on your education level, prior work experience, and employer. However, a computer science degree can help prepare you for various occupations, including information security analyst, computer systems analyst, computer and information research scientist, and network and computer systems administrator.\nDo computer science degrees increase job stability and salary potential?\nIn general, the more education you have, the higher your salary and the greater your job stability. In 2023, the [National Center for Education Statistics](https://nces.ed.gov/programs/coe/indicator/cba/annual-earnings) reported that full-time workers aged 25-34 with a bachelor's degree earned an annual average of $61,600 compared to $74,600 for same-age workers with a master's degree.\nAre computer jobs going away because of AI?\nWe cannot be certain about how AI will impact computer jobs in the future. Though AI can generate code for computer programming or analyze data, [some industry experts predict](https://www.businessinsider.com/chatgpt-jobs-at-risk-replacement-artificial-intelligence-ai-labor-trends-2023-02) that AI will actually augment tech professionals' work to be more efficient rather than replace them.\nLast reviewed June 21, 2023.\nRecommended Reading\nTake the next step toward your future.\nDiscover programs you’re interested in and take charge of your education.",
    "publish_date": "2022-02-10 17:45:27+00:00",
    "summary": "Use our guide to learn more about some of the best careers in computer science, including the different computer science fields of work and how to find a job in this growing space.\nTop Five Computer Science Jobs by SalaryTop Five Computer Science Jobs by OutlookTop Computer Science Degree Jobs by Career Outlook Computer Science Career Job Outlook, 2022-32 Information Security Analysts +32% Software Developers +25% Computer and Information Research Scientists +23% Web Developers and Digital Designers +16% Computer Systems Analysts +10%Salary Potential and Career Outlook for Computer ScientistsThe U.S. Bureau of Labor Statistics (BLS) projects 23% growth for computer science and information technology jobs between 2022 and 2032 — a much-faster-than-average growth rate, which may indicate continued demand for workers with tech skills as society continues to incorporate technology into everyday life.\nGet a Tech Job With a Computer Science DegreeMany careers in computer science — like software developer, information security analyst, and database administrator — typically require a bachelor's degree in computer science.\nIn some cases, you can qualify for entry-level tech positions after completing a computer science bootcamp and/or earning computer science certifications.\nFAQ About Computer Science Degrees and JobsDo you need a computer science degree to get a job in tech?",
    "keywords": [
      "science",
      "information",
      "degree",
      "research",
      "careers",
      "professionals",
      "workers",
      "jobs",
      "tech",
      "software",
      "computer"
    ],
    "prices": [
      {
        "amount": 61.0,
        "currency": "$"
      },
      {
        "amount": 74.0,
        "currency": "$"
      },
      {
        "amount": 145.0,
        "currency": "$"
      },
      {
        "amount": 132.0,
        "currency": "$"
      },
      {
        "amount": 129.0,
        "currency": "$"
      },
      {
        "amount": 120.0,
        "currency": "$"
      },
      {
        "amount": 101.0,
        "currency": "$"
      },
      {
        "amount": 104.0,
        "currency": "$"
      },
      {
        "amount": 45.0,
        "currency": "$"
      },
      {
        "amount": 119.0,
        "currency": "$"
      },
      {
        "amount": 61.0,
        "currency": "$"
      },
      {
        "amount": 74.0,
        "currency": "$"
      }
    ],
    "dates": [
      "2024-08-19T00:00:00",
      "2022-02-10T00:00:00",
      "2024-08-19T00:00:00",
      "2022-02-10T00:00:00",
      "2024-08-19T00:00:00",
      "2022-02-10T00:00:00",
      "2024-08-19T00:00:00"
    ],
    "named_entities": {
      "WORK_OF_ART": [
        "Popular Online Programs\nLearn",
        "Facebook, Meta",
        "Popular Online Programs\nLearn"
      ],
      "ORG": [
        "Top Five Computer Science Jobs",
        "Salary\nComputer Science Career",
        "Top Five Computer Science Jobs",
        "Outlook\nComputer Science Career",
        "Digital Designers",
        "Career Outlook for Computer Scientists",
        "U.S. Bureau",
        "BLS",
        "BLS",
        "Microsoft",
        "Microsoft",
        "Microsoft",
        "Alphabet:",
        "Google",
        "Apple",
        "iPhone",
        "Mac",
        "Apple",
        "Apple",
        "Amazon",
        "Amazon",
        "Amazon",
        "Meta",
        "U.S. Department of Defense",
        "the Department of Defense (DoD",
        "Nike",
        "NIKE",
        "Android",
        "Intel",
        "IBM",
        "Find Your Computer Science Career",
        "Computer Engineer](https://www.computerscience.org",
        "Forensics Investigator](https://www.computerscience.org",
        "Game Designer](https://www.computerscience.org",
        "Discover Resources for Working in Computer Science\nProfessional",
        "IAENG Society of Software",
        "Meetup",
        "Help for Computer Science Students",
        "ACM",
        "CRA",
        "IEEE Computer Society](https://www.computer.org/",
        "Association for Women",
        "AWC",
        "InfoSec Institute](https://www.infosecinstitute.com/",
        "National Center for Education Statistics](https://nces.ed.gov",
        "AI"
      ],
      "PERSON": [
        "Salary",
        "Salary Potential",
        "Converse",
        "Recommended Reading\nTake"
      ],
      "DATE": [
        "May 2023",
        "2022-32",
        "between 2022 and 2032",
        "annual",
        "May 2023",
        "1975",
        "quarterly",
        "February 2024",
        "2004",
        "1972",
        "2023",
        "annual",
        "25-34",
        "annual",
        "trends-2023-02",
        "21, 2023"
      ],
      "MONEY": [
        "145,080](https://www.bls.gov",
        "132,270](https://www.bls.gov",
        "120,360](https://www.bls.gov",
        "101,510](https://www.bls.gov",
        "104,920",
        "45,760",
        "$119.6 billion",
        "61,600",
        "74,600"
      ],
      "PERCENT": [
        "23%"
      ],
      "CARDINAL": [
        "two",
        "221,000",
        "120,000",
        "one",
        "38",
        "860",
        "250"
      ],
      "GPE": [
        "Redmond",
        "Washington",
        "U.S.",
        "AI",
        "U.S.",
        "Jordan",
        "Cisco",
        "Washington, DC",
        "AI",
        "AI",
        "AI"
      ],
      "NORP": [
        "American"
      ],
      "LOC": [
        "North America"
      ],
      "FAC": [
        "Career"
      ]
    },
    "key_phrases": [
      "computer science",
      "science jobs",
      "information",
      "software",
      "degree",
      "tech",
      "careers",
      "security analyst",
      "job",
      "systems"
    ]
  }
}