{
  "url": "https://au.jora.com/Computer-Science-Graduate-jobs-in-Australia",
  "title": "718 Computer Science Graduate jobs in Australia | Jora",
  "extracted_data": {
    "title": "Computer Science Graduate jobs in Australia - Jora",
    "main_content": "Responsibilities :\n• Assist in designing and implementing ETL pipelines across a range of technologies\nand working with clients to integrate pipelines with their source systems\n• Assist in development and optimization of a next-generation analytics platform that\nutilises numerous data sources\n• Assist in extracting and transforming data to support new analyses supported by\nhigh-frequency, highly granular data flows\n• Use data to create models that depict trends in the customer base and consumer\npopulation as a whole.\n• Develops reports and analysis\n• Training end user on new reports and dashboard\n• Help and develop reusable code and libraries for future use.\n• Maintain an in-depth understanding of technologies and stay abreast of current\nindustry trends and emerging technologies\n• Passionate to learn new technology and willing to go beyond your comfort zone.\nESSENTIAL SKILLS:\n• A high-level of motivation and demonstrable ability to solve complex problems and\ndeliver solutions under tight timelines\n• The ability to help develop a suite of databases that will support a cutting-edge web\napplication\n• Good understanding and some experience with SQL Server Integration Services or\nother ETL tools\n• Exposure to Oracle and SQL Server 2016\n• Exposure to Healthcare data preferred but not essential\n• Exposure with Amazon AWS or Azure services desired\n• Exposure writing automated tests for data pipelines\n• Exposure to BI Tools : Tableau, Power BI,Google Data Studio etc..\n• Good understanding and exposure with one or more database engines, including\nMySQL, Postgres, MS SQL, etc...\n• Be a critical thinker with strong analytical and problem-solving skills\n• Be passionate about delivering high quality work\nQUALIFICATIONS & REQUIREMENTS\n• Bachelor’s degree with minimum 3-5 years of development experience\n• 3+ years' experience with exposure to data in the context of application development,\ndata warehousing, migration, or data analysis\nJob Type : Full Time\nSALARY: $130000 per Year( Including Super)\nSummary of role requirements:- Looking for candidates available to work:\n- Monday: Morning, Afternoon, Evening\n- Tuesday: Morning, Afternoon, Evening\n- Wednesday: Morning, Afternoon, Evening\n- Thursday: Morning, Afternoon, Evening\n- Friday: Morning, Afternoon, Evening\n- 2-3 years of relevant work experience required for this role\n- Working rights required for this role",
    "summary": "Responsibilities :• Assist in designing and implementing ETL pipelines across a range of technologiesand working with clients to integrate pipelines with their source systems• Assist in development and optimization of a next-generation analytics platform thatutilises numerous data sources• Assist in extracting and transforming data to support new analyses supported byhigh-frequency, highly granular data flows• Use data to create models that depict trends in the customer base and consumerpopulation as a whole.\n• Develops reports and analysis• Training end user on new reports and dashboard• Help and develop reusable code and libraries for future use.\n• Maintain an in-depth understanding of technologies and stay abreast of currentindustry trends and emerging technologies • Passionate to learn new technology and willing to go beyond your comfort zone.\nESSENTIAL SKILLS: • A high-level of motivation and demonstrable ability to solve complex problems and deliver solutions under tight timelines • The ability to help develop a suite of databases that will support a cutting-edge web application • Good understanding and some experience with SQL Server Integration Services or other ETL tools • Exposure to Oracle and SQL Server 2016 • Exposure to Healthcare data preferred but not essential • Exposure with Amazon AWS or Azure services desired • Exposure writing automated tests for data pipelines • Exposure to BI Tools : Tableau, Power BI,Google Data Studio etc.. • Good understanding and exposure with one or more database engines, including MySQL, Postgres, MS SQL, etc... • Be a critical thinker with strong analytical and problem-solving skills • Be passionate about delivering high quality workQUALIFICATIONS & REQUIREMENTS • Bachelor’s degree with minimum 3-5 years of development experience • 3+ years' experience with exposure to data in the context of application development, data warehousing, migration, or data analysisJob Type : Full TimeSALARY: $130000 per Year( Including Super)",
    "keywords": [
      "exposure",
      "graduate",
      "science",
      "pipelines",
      "australia",
      "understanding",
      "718",
      "trends",
      "data",
      "development",
      "jobs",
      "assist",
      "experience",
      "computer",
      "tools",
      "sql"
    ],
    "prices": [
      {
        "amount": 30.0,
        "currency": "$"
      },
      {
        "amount": 50.0,
        "currency": "$"
      },
      {
        "amount": 70.0,
        "currency": "$"
      },
      {
        "amount": 90.0,
        "currency": "$"
      },
      {
        "amount": 110.0,
        "currency": "$"
      },
      {
        "amount": 30.0,
        "currency": "$"
      },
      {
        "amount": 50.0,
        "currency": "$"
      },
      {
        "amount": 70.0,
        "currency": "$"
      },
      {
        "amount": 90.0,
        "currency": "$"
      },
      {
        "amount": 110.0,
        "currency": "$"
      },
      {
        "amount": 30.0,
        "currency": "$"
      },
      {
        "amount": 50.0,
        "currency": "$"
      },
      {
        "amount": 70.0,
        "currency": "$"
      },
      {
        "amount": 90.0,
        "currency": "$"
      },
      {
        "amount": 110.0,
        "currency": "$"
      },
      {
        "amount": 70.0,
        "currency": "$"
      },
      {
        "amount": 80.0,
        "currency": "$"
      },
      {
        "amount": 80.0,
        "currency": "$"
      },
      {
        "amount": 80.0,
        "currency": "$"
      },
      {
        "amount": 130000.0,
        "currency": "$"
      }
    ],
    "dates": [
      "2024-11-16T00:00:00"
    ],
    "named_entities": {
      "ORG": [
        "• Assist",
        "• Assist",
        "• Good",
        "SQL Server Integration Services",
        "• Exposure",
        "SQL Server",
        "• Exposure",
        "Healthcare",
        "• Exposure",
        "• Exposure",
        "• Exposure",
        "Tableau, Power BI",
        "Google Data Studio",
        "• Good",
        "MySQL, Postgres",
        "MS SQL",
        "QUALIFICATIONS & REQUIREMENTS\n• Bachelor’s"
      ],
      "PERSON": [
        "• Training",
        "• Help",
        "Oracle"
      ],
      "DATE": [
        "2016",
        "3-5 years",
        "3+ years'",
        "Monday",
        "Tuesday",
        "Wednesday",
        "Thursday",
        "Friday"
      ],
      "MONEY": [
        "130000"
      ],
      "TIME": [
        "Morning",
        "Evening",
        "Morning",
        "Evening",
        "Morning",
        "Evening",
        "Morning",
        "Evening",
        "Morning"
      ]
    },
    "key_phrases": [
      "Assist",
      "source systems",
      "Exposure",
      "data",
      "highly granular",
      "next-generation analytics",
      "analytics platform",
      "utilises numerous",
      "create models",
      "customer base"
    ]
  }
}