{
  "url": "https://www.glassdoor.com.au/Job/entry-level-computer-science-graduate-jobs-SRCH_KO0,37.htm",
  "title": "6 Entry level computer science graduate jobs in Australia | Glassdoor",
  "extracted_data": {
    "title": "6 Entry level computer science graduate jobs in Australia",
    "main_content": "We power insights for better, safer workplaces…together.\nKickstart your Tech Career: Junior Software Developer (Open to new Graduates and multiple roles available).\nAre you a recent graduate ready to dive into the world of software development? Do you have a passion for coding, problem-solving, and continuous learning? We’re on the hunt for motivated individuals like you to join our team!\nWe are seeking a dynamic and recently graduated Software Developer. As a Junior Software Developer, you will support the design, development, and maintenance of our software solutions. This role offers a fantastic chance to grow your technical skills while working closely with experienced developers. You'll be part of a collaborative team, contributing your creativity and fresh perspective to build and maintain reliable, high-quality cloud-based SaaS products that meet customer needs and business objectives.\nOUR TEAM’S STRENGTH COMES FROM EVERYONE’S INDIVIDUALITY\nAbout you:\n- Education: Bachelor’s degree in Computer Science, Software Engineering, or a related field.\n- Experience: Previous internship or entry-level experience is a plus, along with a portfolio of coding projects.\n- Technical Skills: Proficiency in relevant programming languages and familiarity with development frameworks (e.g. C#, Typescript/JavaScript, React, NodeJS, Flutter). A willingness to learn new frameworks and technologies to bring great products to market.\n- Tools: Basic knowledge of software development tools and version control systems (e.g., Git).\n- Methodologies: Understanding of Agile principles and the Scrum framework, along with a willingness to skill up in DevOps practices.\n- Mindset: Strong desire to learn and grow in the software development field, with a continuous learning mindset.\nDELIVERING THE GOOD, STRIVING FOR THE GREAT\nPosition responsibilities include but are not limited to:\nSoftware Development:\n- Assist in designing, coding, testing, and debugging software applications based on technical specifications.\n- Write clean, efficient, and scalable code that meets project requirements.\n- Help maintain and improve existing systems, resolving issues to support smooth business operations.\nTechnical Analysis:\n- Collaborate with team members to analyse user needs and software requirements.\n- Participate in technical discussions, contributing ideas for potential improvements and innovative solutions.\nCollaboration:\n- Work closely with cross-functional teams, including designers, product managers, and senior developers, to deliver integrated software solutions.\n- Communicate effectively to ensure clarity on project goals and tasks.\nProblem-Solving:\n- Help identify and address software defects and performance issues.\n- Assist in debugging and resolving technical challenges in a timely manner.\nContinuous Improvement:\n- Stay updated on emerging technologies, industry trends, and best practices.\n- Apply new knowledge to enhance the development process and contribute to delivering cutting-edge solutions.\nDocumentation & Code Review:\n- Contribute to creating clear technical documentation, including design specifications and user guides.\n- Participate in code reviews, offering and receiving constructive feedback to ensure code quality.\nARE YOU READY TO BE A KINATICAN?\nWhere our passion, talent, delivery and impact collide our purpose lies. Powering insights for better, safer workplaces, helping organisations to know their people – we are a global leader in Reg-Tech. Our technology helps organisations to know their people.\n- Flexible and supportive work environment\n- A culture of development and recognition, we want our people to thrive!\n- Attend our Friday Funaticans in person and virtual events\n- Bright, spacious office in the Perth CBD\n- Work for an ASX listed company and a leader in Reg-Tech\nTELL US ABOUT YOURSELF\nApply with your resume (with cover letter appreciated).\nResearch shows that while men apply to jobs when they meet an average of 60% of the criteria, women and other marginalised individuals tend to only apply when they check every box. If you think you have what it takes (a growth mindset) but don't necessarily meet every single point on the job description, please still get in touch. We'd love to have a chat and see if you could be a great fit.",
    "summary": "Are you a recent graduate ready to dive into the world of software development?\nProficiency in relevant programming languages and familiarity with development frameworks (e.g.\nTools: Basic knowledge of software development tools and version control systems (e.g., Git).\nBasic knowledge of software development tools and version control systems (e.g., Git).\nMindset: Strong desire to learn and grow in the software development field, with a continuous learning mindset.",
    "keywords": [
      "graduate",
      "science",
      "level",
      "entry",
      "systems",
      "australia",
      "technical",
      "willingness",
      "development",
      "jobs",
      "coding",
      "code",
      "software",
      "computer",
      "technologies",
      "tools",
      "frameworks"
    ],
    "prices": [
      {
        "amount": 106.0,
        "currency": "$"
      },
      {
        "amount": 190.0,
        "currency": "$"
      },
      {
        "amount": 65.0,
        "currency": "$"
      },
      {
        "amount": 75.0,
        "currency": "$"
      },
      {
        "amount": 85.0,
        "currency": "$"
      },
      {
        "amount": 96.0,
        "currency": "$"
      },
      {
        "amount": 65.0,
        "currency": "$"
      },
      {
        "amount": 80.0,
        "currency": "$"
      },
      {
        "amount": 119.0,
        "currency": "$"
      },
      {
        "amount": 142.0,
        "currency": "$"
      },
      {
        "amount": 106.0,
        "currency": "$"
      },
      {
        "amount": 190.0,
        "currency": "$"
      },
      {
        "amount": 106.0,
        "currency": "$"
      },
      {
        "amount": 190.0,
        "currency": "$"
      },
      {
        "amount": 142.0,
        "currency": "$"
      },
      {
        "amount": 72.0,
        "currency": "$"
      },
      {
        "amount": 130.0,
        "currency": "$"
      },
      {
        "amount": 72.0,
        "currency": "$"
      },
      {
        "amount": 130.0,
        "currency": "$"
      },
      {
        "amount": 72.0,
        "currency": "$"
      },
      {
        "amount": 130.0,
        "currency": "$"
      },
      {
        "amount": 72.0,
        "currency": "$"
      },
      {
        "amount": 130.0,
        "currency": "$"
      },
      {
        "amount": 1.0,
        "currency": "$"
      },
      {
        "amount": 2.0,
        "currency": "$"
      },
      {
        "amount": 1.0,
        "currency": "$"
      },
      {
        "amount": 2.0,
        "currency": "$"
      },
      {
        "amount": 1.0,
        "currency": "$"
      },
      {
        "amount": 2.0,
        "currency": "$"
      },
      {
        "amount": 1.0,
        "currency": "$"
      },
      {
        "amount": 2.0,
        "currency": "$"
      }
    ],
    "dates": [
      "2024-11-15T00:00:00",
      "2023-12-04T00:00:00",
      "2023-07-19T00:00:00"
    ],
    "named_entities": {
      "PRODUCT": [
        "Graduates"
      ],
      "ORG": [
        "Software Developer",
        "a Junior Software Developer",
        "TEAM",
        "INDIVIDUALITY",
        "Computer Science, Software Engineering",
        "Typescript/JavaScript",
        "DevOps",
        "Problem-Solving",
        "Documentation & Code Review",
        "KINATICAN",
        "Reg-Tech",
        "ASX",
        "Reg-Tech"
      ],
      "GPE": [
        "React",
        "Mindset",
        "Perth CBD\n-",
        "US"
      ],
      "PERSON": [
        "Git",
        "Scrum"
      ],
      "NORP": [
        "Agile",
        "Funaticans"
      ],
      "DATE": [
        "Friday"
      ],
      "PERCENT": [
        "60%"
      ]
    },
    "key_phrases": [
      "Software",
      "Tech Career",
      "development",
      "code",
      "Apply",
      "Junior",
      "graduate ready",
      "power insights",
      "Work",
      "Mindset"
    ]
  }
}