{
  "url": "https://gmc-studies.com/job-opportunities-after-computer-science-in-australia/",
  "title": "Job Opportunities for Computer Science Graduates in Australia 2025 -",
  "extracted_data": {
    "title": "Job Opportunities for Computer Science Graduates in Australia 2025 -",
    "main_content": "Computer science is changing and growing quickly, which is creating a lot of work possibilities in many different fields. Australia has become a great place for computer science graduates to work because it has a strong economy, a high demand for tech workers, and a welcoming environment for foreign students.\nThe country has great education programs and easy ways to get work visas and permanent residency, which makes it even more appealing to people who want to start their jobs abroad.\nWe will talk in depth about the job market after learning computer science in Australia in this blog post. We will look at current market trends, top job roles, key industries, and a lot more.\nCurrent Job Market Trends in Australia\nAs the world becomes increasingly digital, the importance of computer science professionals is at an all-time high. The Australian job market is experiencing a surge in demand for skilled workers in IT-related sectors. Technological advancements, the rise of startups, and government initiatives to promote innovation are some of the factors driving this trend.\nHigh-Demand Sectors\nThe digital economy in Australia is booming, making it an opportune time for computer science graduates to enter the workforce. Some of the high-demand sectors include:\n- Software Development: Software developers are essential for creating applications, systems, and platforms that businesses rely on. As companies continue to digitize their processes, the need for experienced software engineers is growing exponentially.\n- Cybersecurity: With the increase in data breaches and cyber-attacks, organizations are prioritizing cybersecurity. Cybersecurity specialists protect sensitive information and create secure networks, making them invaluable to both private and public sector organizations.\n- Data Science: The ability to analyze and interpret large volumes of data is crucial for businesses looking to gain insights and drive decision-making. Data scientists are sought after for their expertise in statistical analysis, machine learning, and data visualization.\n- Artificial Intelligence and Machine Learning: As industries integrate AI technologies to enhance efficiency and automate processes, the demand for AI/ML engineers is skyrocketing. These professionals develop algorithms and models that enable machines to learn from data and make predictions.\nImpact of Digital Transformation\nThe shift to digital is changing how companies in every industry work. More and more businesses are using cutting edge technologies like cloud computing, the Internet of Things, and big data analytics. Because of this ongoing shift, we need trained workers who can adapt to these changes. Because of this, there is a greater need for computer science graduates who can change the way businesses do things in new ways.\nTech companies aren’t the only ones going through this fast change; healthcare and finance are also going through big changes. Telemedicine and financial solutions, for example, have become very popular, and they need tech-savvy people to run and improve them.\nGovernment Initiatives and Industry Growth\nThe Australian government recognizes the crucial role that technology plays in the future of the economy. Various initiatives are being launched to nurture the tech industry through investments in education, research, and infrastructure. Programs promoting entrepreneurship and supporting startups have been introduced, contributing to a dynamic job market for computer science graduates.\nMoreover, universities and vocational schools are collaborating with tech firms to ensure that curricula align with industry needs. This partnership ensures that graduates possess the skills employers are seeking, enhancing their employability.\nTop Job Roles for Computer Science Graduates\nComputer science majors can go in a lot of different directions, so it’s important to know which jobs are the most in demand and what they involve. After finishing school, the following are some of the best jobs that people can get.\nSoftware Engineer/Developer\nTypical Responsibilities:\nSoftware engineers are responsible for designing, developing, testing, and maintaining software applications. They play a vital role in the creation of systems that require robust functionality and performance. Tasks may include writing code, conducting unit tests, debugging issues, and collaborating with cross-functional teams to deliver software solutions aligned with client requirements.\nRequired Skills and Qualifications:\nTo thrive as a software developer, proficiency in programming languages such as Java, Python, or C++ is necessary. Strong problem-solving skills, attention to detail, and familiarity with software development methodologies (e.g., Agile) are also critical. A Bachelor’s degree in Computer Science or related fields is typically required, along with practical experience through internships or projects.\nAverage Salary Ranges:\nIn Australia, software engineers can expect to earn competitive salaries, generally ranging between AUD 70,000 to AUD 120,000 per year depending on experience and expertise. Senior roles or specialized positions, such as full-stack developers, may command even higher remuneration.\nJob Growth Prospects:\nThe job outlook for software developers remains strong, with growth projected over the next decade. As technology continues to evolve and businesses seek to enhance their digital offerings, the demand for skilled developers will likely increase correspondingly.\nData Scientist/Analyst\nTypical Responsibilities:\nData scientists analyze complex datasets to extract valuable insights that inform business strategies. Their responsibilities often include data mining, statistical modeling, and visualizing data findings. Collaborating with stakeholders to understand their data needs and presenting actionable recommendations is also part of their role.\nRequired Skills and Qualifications:\nA solid foundation in statistics, mathematics, and programming is essential for data scientists. Proficiency in tools such as R, Python, SQL, and experience with data visualization software (e.g., Tableau) are highly sought after. Most individuals in this field hold at least a Bachelor’s degree, while many also possess advanced degrees in Data Science or a related discipline.\nAverage Salary Ranges:\nData scientists in Australia enjoy lucrative salaries, with average annual earnings typically between AUD 90,000 and AUD 150,000. Depending on experience and specialization, compensation can be significantly higher for senior roles.\nJob Growth Prospects:\nThe demand for data scientists is expected to grow substantially as organizations increasingly rely on data-driven decision-making. Employers are actively seeking professionals who can turn data into actionable insights, ensuring favorable job prospects for graduates.\nCybersecurity Specialist\nTypical Responsibilities:\nCybersecurity specialists defend organizations against cyber threats. Their tasks involve monitoring networks for security breaches, implementing security measures, conducting vulnerability assessments, and responding to incidents when they arise. Training staff on best practices for information security may also be part of their duties.\nRequired Skills and Qualifications:\nTo excel in this role, one must possess a strong understanding of network protocols, encryption, firewalls, and intrusion detection systems. Certifications such as CISSP (Certified Information Systems Security Professional) and CISM (Certified Information Security Manager) are often advantageous. A degree in Computer Science, Information Technology, or Cybersecurity is typically required.\nAverage Salary Ranges:\nIn Australia, cybersecurity specialists can earn between AUD 80,000 and AUD 140,000 annually, with potential for higher earnings as professionals gain experience and expertise.\nJob Growth Prospects:\nGiven the rising threats of cybercrime, job opportunities in cybersecurity are projected to grow significantly. Organizations are increasingly investing in cybersecurity measures, leading to heightened demand for skilled professionals.\nAI/ML Engineer\nTypical Responsibilities:\nAI and machine learning engineers focus on developing algorithms and models that enable software applications to learn and adapt. Their work involves training machine learning models, optimizing performance, and integrating AI capabilities into existing systems.\nRequired Skills and Qualifications:\nA thorough knowledge of machine learning frameworks (e.g., TensorFlow, PyTorch) and strong programming skills in languages like Python or Java are vital for success in this role. Typically, candidates possess degrees in Computer Science, Artificial Intelligence, or related fields, often coupled with relevant certifications.\nAverage Salary Ranges:\nAI/ML engineers in Australia can anticipate earning salaries ranging from AUD 100,000 to AUD 160,000 or more annually, reflecting the specialized nature of the role.\nJob Growth Prospects:\nThe demand for AI and ML engineers is surging as industries leverage artificial intelligence to streamline operations. As technology continues to advance, job opportunities in this space are expected to grow.\nCloud Computing Specialist\nTypical Responsibilities:\nCloud computing specialists manage cloud environments, ensuring efficient deployment, scaling, and security of cloud-based services. They work with technologies such as AWS, Azure, or Google Cloud to build and maintain applications and solutions.\nRequired Skills and Qualifications:\nStrong technical skills in cloud architecture and management, familiarity with APIs, and understanding of security protocols are essential. Professionals in this field usually have a background in Computer Science or Information Technology.\nAverage Salary Ranges:\nSalaries for cloud computing specialists typically range from AUD 90,000 to AUD 130,000 per year, depending on experience and skill level.\nJob Growth Prospects:\nWith an increasing number of businesses migrating to the cloud, the job outlook for cloud computing specialists is promising. As organizations seek to optimize their cloud strategies, the need for skilled professionals in this domain will continue to rise.\nWeb Developer/Full Stack Developer\nTypical Responsibilities:\nWeb developers design and create websites, focusing on both front-end and back-end development. Full stack developers handle all aspects of web development, working with HTML, CSS, JavaScript, databases, and server-side languages.\nRequired Skills and Qualifications:\nExperience with web development frameworks (e.g., React, Angular, Node.js) and proficiency in programming languages are vital. Many web developers possess degrees in Computer Science or Web Development.\nAverage Salary Ranges:\nWeb developers in Australia can earn between AUD 70,000 and AUD 120,000, depending on their skills and experience.\nJob Growth Prospects:\nThe demand for web developers remains steady as businesses establish and enhance their online presence. The versatility of web development skills contributes to favorable job opportunities in this field.\nIndustries Offering Opportunities for Computer Science Graduates\nComputer science graduates are not confined to a single sector; instead, they have diverse opportunities across multiple industries. Here are some key sectors where computer science professionals are making a significant impact.\nInformation Technology (IT) Services\nThe IT services industry is the backbone of technological advancement, encompassing application development, system integration, consulting, and managed services. As businesses increasingly rely on technology, the demand for IT professionals continues to grow. Roles in this sector include software developers, system analysts, and IT consultants.\nFinancial Services\nThe financial sector is embracing digital transformation, leading to a surge in demand for tech talent. Fintech companies, banks, and insurance firms require expertise in cybersecurity, data analysis, and software development to create innovative financial solutions. Careers in this sector may involve developing secure online banking platforms, fraud detection systems, and data-driven financial models.\nHealthcare and Biotechnology\nTechnology is revolutionizing healthcare and biotechnology, with advancements in telemedicine, electronic health records, and personalized medicine. Computer science graduates can contribute to developing healthcare applications, managing patient data, and implementing AI-driven diagnostic tools. Opportunities in this sector include health informatics specialists, bioinformatics analysts, and software developers.\nEducation and E-Learning\nThe education sector is undergoing significant changes with the rise of online learning platforms and educational technology. Computer science professionals play a crucial role in developing e-learning applications, managing learning management systems, and enhancing digital literacy. Careers in this sector include instructional designers, educational software developers, and IT administrators.\nGovernment and Public Sector\nGovernment agencies are leveraging technology to improve public services, enhance cybersecurity, and promote transparency. Computer science graduates can work on projects related to digital government services, data management, and public safety. Roles in this sector include IT project managers, cybersecurity analysts, and data scientists.\nStartups and Entrepreneurship\nAustralia’s vibrant startup ecosystem offers exciting opportunities for computer science graduates to innovate and create their ventures. Startups often require tech talent to develop products, build scalable systems, and manage technical operations. Graduates with an entrepreneurial spirit can explore roles as founders, CTOs, or technical advisors.\nPathways to Permanent Residency\nAustralia provides favorable pathways for international graduates to secure permanent residency, making it an attractive destination for those looking to build their careers. Here are some common pathways:\n[Australia Permanent Residency for Bangladeshi Students](https://gmc-studies.com/australia-permanent-residency-for-bangladeshi-students/)\nSkilled Independent Visa (Subclass 189)\nThe Skilled Independent Visa is a points-based visa for skilled workers who are not sponsored by an employer or family member. Graduates can apply for this visa based on their qualifications, work experience, and English language proficiency.\nSkilled Nominated Visa (Subclass 190)\nThe Skilled Nominated Visa is a points-based [visa for skilled workers](https://immi.homeaffairs.gov.au/visas/permanent-resident/visa-options) nominated by an Australian state or territory government. Applicants must meet the nomination requirements of the state or territory and have skills relevant to the local job market.\nTemporary Graduate Visa (Subclass 485)\nThe Temporary Graduate Visa allows international students who have recently graduated from an Australian institution to live and work in Australia temporarily. This visa provides graduates with valuable work experience and the opportunity to improve their skills and meet the requirements for permanent residency.\nEmployer-Sponsored Visas\nEmployer-sponsored visas, such as the Temporary Skill Shortage (TSS) visa and the Employer Nomination Scheme (ENS) visa, allow Australian employers to sponsor skilled workers for temporary or permanent residency. Graduates with job offers from Australian employers can explore these pathways.\nConclusion\nAustralia offers a wealth of opportunities for computer science graduates, with a thriving job market, diverse industries, and favorable pathways to permanent residency. By pursuing a career in this dynamic field, graduates can contribute to technological advancements, drive innovation, and enjoy a rewarding professional journey. Whether you’re interested in software development, data science, cybersecurity, or AI, Australia provides a supportive environment for achieving your career goals.",
    "authors": [
      "Tanvir Khan"
    ],
    "publish_date": "2024-09-18 09:50:38+06:00",
    "summary": "High-Demand SectorsThe digital economy in Australia is booming, making it an opportune time for computer science graduates to enter the workforce.\nPrograms promoting entrepreneurship and supporting startups have been introduced, contributing to a dynamic job market for computer science graduates.\nIndustries Offering Opportunities for Computer Science GraduatesComputer science graduates are not confined to a single sector; instead, they have diverse opportunities across multiple industries.\nStartups and EntrepreneurshipAustralia’s vibrant startup ecosystem offers exciting opportunities for computer science graduates to innovate and create their ventures.\nConclusionAustralia offers a wealth of opportunities for computer science graduates, with a thriving job market, diverse industries, and favorable pathways to permanent residency.",
    "keywords": [
      "job",
      "cybersecurity",
      "science",
      "developers",
      "australia",
      "2025",
      "opportunities",
      "graduates",
      "data",
      "visa",
      "software",
      "computer",
      "skills"
    ],
    "dates": [
      "2024-09-18T00:00:00",
      "2024-09-18T00:00:00",
      "2024-09-18T00:00:00",
      "2024-09-18T00:00:00",
      "2024-09-18T00:00:00"
    ],
    "named_entities": {
      "GPE": [
        "Australia",
        "Australia",
        "Australia",
        "Australia",
        "Australia",
        "Tableau",
        "Australia",
        "Australia",
        "Australia",
        "AI",
        "React",
        "Node.js",
        "Australia",
        "Entrepreneurship",
        "Australia",
        "Australia",
        "australia",
        "Australia",
        "Australia",
        "AI",
        "Australia"
      ],
      "NORP": [
        "Australian",
        "Australian",
        "Australian",
        "Australian",
        "Australian",
        "Australian"
      ],
      "ORG": [
        "AI",
        "AI/ML",
        "Digital Transformation",
        "Government Initiatives and Industry",
        "Software Engineer/Developer\nTypical Responsibilities",
        "Bachelor",
        "Computer Science",
        "AUD",
        "Data Scientist/Analyst",
        "SQL",
        "Bachelor",
        "Data Science",
        "Cybersecurity Specialist\nTypical Responsibilities",
        "CISSP (Certified Information Systems Security Professional",
        "CISM (Certified Information Security",
        "Computer Science, Information Technology",
        "Cybersecurity",
        "AUD",
        "AI/ML Engineer\nTypical Responsibilities",
        "AI",
        "TensorFlow",
        "PyTorch",
        "Computer Science, Artificial Intelligence",
        "AI/ML",
        "AUD",
        "ML",
        "AWS",
        "Computer Science or Information Technology",
        "AUD",
        "HTML",
        "CSS",
        "JavaScript",
        "Computer Science or Web Development",
        "Information Technology",
        "Financial Services",
        "Healthcare",
        "Biotechnology\nTechnology",
        "E-Learning",
        "Australia Permanent Residency for Bangladeshi",
        "Skilled Independent Visa",
        "The Skilled Independent Visa",
        "Skilled Nominated Visa",
        "The Skilled Nominated Visa",
        "Employer-Sponsored",
        "the Temporary Skill Shortage",
        "TSS",
        "the Employer Nomination Scheme",
        "ENS"
      ],
      "PERSON": [
        "Required Skills",
        "Java",
        "C++",
        "Required Skills",
        "Required Skills",
        "Required Skills",
        "Python",
        "Java",
        "Cloud Computing Specialist",
        "Google Cloud",
        "Required Skills",
        "Required Skills"
      ],
      "QUANTITY": [
        "between AUD 70,000"
      ],
      "CARDINAL": [
        "120,000",
        "150,000",
        "140,000",
        "100,000",
        "160,000",
        "90,000",
        "130,000",
        "120,000",
        "189",
        "190",
        "485"
      ],
      "DATE": [
        "the next decade",
        "annual",
        "annually",
        "annually"
      ],
      "MONEY": [
        "between AUD 80,000"
      ],
      "FAC": [
        "Startups"
      ],
      "LANGUAGE": [
        "English"
      ]
    },
    "key_phrases": [
      "Computer science",
      "science graduates",
      "data",
      "job",
      "Australia",
      "Growth Prospects",
      "AUD",
      "Software",
      "skills",
      "Visa"
    ]
  }
}