{
  "url": "https://www.coursera.org/articles/computer-science-jobs-for-the-future",
  "title": "What Can You Do with a Computer Science Degree? 10 In-Demand Fields | Coursera",
  "extracted_data": {
    "title": "What Can You Do with a Computer Science Degree? 10 In-Demand Fields",
    "main_content": "Earning your bachelor's or master's degree in computer science can lead to exciting opportunities across a number of industries.\nComputer and information technology (IT)-related careers are projected to grow much faster than the average for all occupations in the coming years, according to the Bureau of Labor Statistics (BLS) [[1](https://www.bls.gov/ooh/computer-and-information-technology/home.htm)]. Earning your [computer science degree](https://www.coursera.org/articles/what-is-computer-science-degree)—either your [bachelor's in computer science](https://www.coursera.org/articles/computer-science-bachelor-degree) or [master's in computer science](https://www.coursera.org/articles/masters-in-computer-science)—opens up numerous career opportunities.\nWhile computer science tends to be thought of as [a hard major](https://www.coursera.org/articles/is-computer-science-hard), it's also considered [a good major](https://www.coursera.org/articles/is-computer-science-a-good-major) because of the job opportunities it can often lead to. In this article, we've compiled ten established and emerging fields that are worth exploring as you get ready to apply for your computer science degree and move into the workforce.\nWhether you're looking for [entry-level computer science jobs](https://www.coursera.org/articles/entry-level-computer-science-jobs) or opportunities that require more training and experience, consider these relevant computer science career paths.\n[Artificial intelligence (AI)](https://www.coursera.org/articles/what-does-ai-stand-for) has been named a key driver of the Fourth Industrial Revolution. We experience AI in our homes, our cars, our businesses, and even in public spaces. Machine learning enables an AI system to learn from data. Working in the field of AI and machine learning means innovating the technology of tomorrow.\nThis industry may be good for you if: You can think creatively and analytically. You want to play a role in transforming the global economy.\nAI and machine learning job titles:\nMachine learning engineer\nAI researcher\nCommon job requirements: Bachelor or Master of Computer Science, knowledge of Python, Java, and R coding languages\nThe growing field of robotics focuses on building robots that can replicate human actions (from building cars to assisting in surgery). A foundation in computer science equips you to program the software that helps physical and virtual bots operate effectively.\nThis industry may be good for you if: You’re interested in computer programming as well as electrical and mechanical engineering. You enjoy hands-on projects.\nRobotics job titles:\nRobotics engineer\nRobotics technician\nSoftware developer\nCommon job requirements: Bachelor’s degree in computer science or software, mechanical, or electrical engineering, experience with computer-aided design (CAD) software, proficiency in C++ or Python.\nLearn more: [5 Robotics Jobs to Consider](https://www.coursera.org/articles/robotics-jobs)\nComputer forensics exists at the intersection of law and computer science. Computer forensics, also called data or digital forensics, deals with the recovery and analysis of digital evidence recovered from computers, networks, and digital storage devices. You might work in a crime lab, law enforcement department, public agency, or private contractor.\nThis industry may be good for you if: you’re naturally inquisitive and are interested in cybercrime and law enforcement.\nComputer forensics job titles:\nDigital forensics specialist\nComputer forensics investigator\nForensic computer analyst\nCommon job requirements: Bachelor’s degree in computer science or computer security, recognized digital forensics certification\nCybersecurity refers to the practice of protecting computer systems, networks, programs, and mobile devices from unauthorized access or digital attacks. Cyberattacks rank among the fastest-growing crimes, fueling global demand for cybersecurity skills.\nEthical hacking takes a proactive approach to cybersecurity by trying to find vulnerabilities before malicious hackers do.\nThis industry is perfect for you if: you naturally think ahead to what could go wrong before it happens. You take a methodical approach to problem-solving.\nCybersecurity job titles:\nSystems engineer\nCybersecurity manager\nCommon job requirements: Bachelor of Computer Science or Master of Business Administration in Information Systems, information security certification like the Certified Information Systems Security Professional (CISSP) or Certified Cloud Security Professional (CCSP)\nRead more: [10 Popular Cybersecurity Certifications](https://www.coursera.org/articles/popular-cybersecurity-certifications)\nWhile video game design isn’t a new industry, it’s one that will likely continue to evolve. As games get more advanced, gaming companies will need more people skilled in designing and programming virtual reality, graphics, game physics, networks, and user interfaces.\nThis industry is perfect for you if: you’re a creative thinker with a passion for video games.\nVideo game design job titles:\nProgrammer\nTechnical support specialist\nCommon job requirements: Bachelor of Computer Science or related field, knowledge of the latest gaming trends, proficiency in C++ or Java programming languages\nWith the emergence of cloud computing technology, companies no longer need their own servers to build products. As the cloud continues to grow, so will the demand for professionals with cloud computing skills, including cloud security, database management, and network architecture.\nThis industry is perfect for you if: you’re interested in how the Internet can help transform businesses.\nCloud computing job titles:\nNetwork architect\nCloud security specialist\nCommon job requirements: Bachelor’s degree in computer science, certification from Google Cloud Platform (GCP), Amazon Web Services (AWS), Cisco, or Microsoft Azure\nLearn more: [5 Cloud Certifications for Your IT Career](https://www.coursera.org/articles/cloud-certifications-for-your-it-career)\nBioinformatics combines mathematics, biology, and computer science to better understand biological data. Scientists in this field use the growing stream of biological data by storing, analyzing, and interpreting big data sets using computer technology.\nThis industry is perfect for you if: You like analyzing facts and working with ideas. You’re interested in biological science as well as computers.\nBioinformatics job titles:\nBioinformatics scientist\nResearch associate\nBioinformatics engineer\nCommon job requirements: Master’s degree in computer science or computational biology, proficiency with Python, Perl, and R programming languages\n[User experience (UX) design](https://www.coursera.org/articles/what-does-a-ux-designer-do) helps shape a customer’s emotions and attitudes when using a particular product, service, or system. Whether for a physical product or, more often, for a website or app, user design is concerned with gathering and analyzing data to craft the most enjoyable and efficient user experience.\nThis industry is perfect for you if: You are interested in human behavior. You want a career where you can use your creativity.\nUX design job titles:\nInformation architect\nCommon job requirements: Bachelor’s degree in human-computer interaction, computer science, or psychology, knowledge of design and prototyping tools like Sketch, InVision, or AdobeXD\nBusinesses are often inundated with data each day, more data than the human mind can make sense of on its own. That’s where [big data analytics](https://www.coursera.org/articles/what-is-big-data-a-laypersons-guide) comes in. This field deals with collecting and analyzing large data sets to find valuable information that can be leveraged to make better business decisions.\nThis industry is perfect for you if: you enjoy mathematics and making sense of large data sets.\nBig data job titles:\nData visualization developer\nBusiness intelligence engineer\nCommon job requirements: Bachelor’s or master’s degree in computer or data science, proficiency with SQL, knowledge of Python, Java, or R programming languages\nPhysical objects around the globe—from thermostats and lightbulbs to toys and audio speakers—are now connected to the internet. The Internet of things (IoT) refers to this collection of devices and the technology used to connect the physical with the digital. As the number of “smart” objects grows, companies will need professionals with the skills to design, develop, and program them.\nThis industry is perfect for you if: you’re a natural tinkerer obsessed with the latest gadgets.\nInternet of things job titles:\nIoT developer\nEmbedded systems designer\nVulnerability analyst\nCommon job requirements: Bachelor of Computer Science, IoT or cloud development certification, proficiency with JavaScript and Python\nNow that you’ve learned about what you can do with a computer science degree, it’s time to take the next step on your career journey.\nDevelop niche skills in high-demand areas like AI through [DeepLearning.AI's Generative AI for Software Development](https://www.coursera.org/professional-certificates/generative-ai-for-software-development).\nLearn about what it’s like to [earn your bachelor’s or master’s in computer science online](https://www.coursera.org/degrees/computer-science). Sign up for more information on degree programs through Coursera, or [contact a Coursera enrollment counselor](mailto:degrees-enrollment@coursera.org) to get your questions answered.\nExperience a degree program for yourself by [sitting in on a degree course](https://www.coursera.org/degrees/master-of-computer-science-illinois/academics) from the University of Illinois.\nRead on for answers to some frequently asked questions about degrees in computer science.\nStudying computer science means learning some complex topics like algorithms and coding. With the right motivation, patience, and an interest in computers, you can find success in this challenging field.\nRead more: [Is Computer Science Hard?](https://www.coursera.org/articles/is-computer-science-hard)\nThe time, effort, and monetary investment of earning a degree potentially opens up well-paying job opportunities in many in-demand fields. Check the job requirements of some positions you’d like to apply to in the future to see if a computer science degree aligns with your career goals.\nRead more: [Bachelor’s Degree in Computer Science: A Guide](https://www.coursera.org/articles/computer-science-bachelor-degree)\nIf you’re organized, pay attention to detail, and enjoy problem solving, computer science could be a good fit. Enhance your understanding of technology and learn skills to empower you to work in the computer careers of the future.\nRead more: [What’s a Computer Scientist? And How to Become One](https://www.coursera.org/articles/computer-scientist)\nThe computer science field was one of the first to allow working from home, even before COVID-19. Whether or not you can work from home depends on your career choice. Jobs in software and web development, programming, and technical support often come with work-from-home opportunities.\nRead more: [10 Remote Work-From-Home Jobs that Pay Well](https://www.coursera.org/articles/remote-work-from-home-jobs)\nYes. Completing a computer science degree online allows you to study from home with the same curriculum and professors as on-campus programs. Some online degree programs offer greater flexibility. You can continue to work, take care of family, or keep up with other obligations while earning your degree.\nRead more: [10 Surprising Benefits of Online Learning](https://www.coursera.org/articles/benefits-of-online-learning)\nUS Bureau of Labor Statistics. \"[Computer and Information Technology Occupations](https://www.bls.gov/ooh/computer-and-information-technology/home.htm), https://www.bls.gov/ooh/computer-and-information-technology/home.htm.\" Accessed January 10, 2023.\nEditorial Team\nCoursera’s editorial team is comprised of highly experienced professional editors, writers, and fact...\nThis content has been made available for informational purposes only. Learners are advised to conduct additional research to ensure that courses and other credentials pursued meet their personal, professional, and financial goals.",
    "keywords": [
      "science",
      "degree",
      "indemand",
      "fields",
      "computer"
    ],
    "prices": [
      {
        "amount": 20.0,
        "currency": "$"
      },
      {
        "amount": 20.0,
        "currency": "$"
      }
    ],
    "dates": [
      "2020-12-14T00:00:00",
      "2024-09-25T00:00:00",
      "2020-12-14T00:00:00",
      "2024-09-25T00:00:00",
      "2024-03-19T00:00:00",
      "2024-10-11T00:00:00",
      "2023-12-12T00:00:00",
      "2024-07-26T00:00:00",
      "2024-01-04T00:00:00",
      "2024-10-08T00:00:00"
    ],
    "named_entities": {
      "DATE": [
        "the coming years",
        "tomorrow",
        "each day",
        "January 10, 2023"
      ],
      "ORG": [
        "the Bureau of Labor Statistics",
        "BLS",
        "AI",
        "CAD",
        "Consider](https://www.coursera.org",
        "Digital",
        "Cybersecurity",
        "Bachelor of Computer Science or Master of Business Administration in Information Systems",
        "the Certified Information Systems Security Professional (CISSP",
        "Certified Cloud Security Professional",
        "Popular Cybersecurity Certifications](https://www.coursera.org",
        "Bachelor of Computer Science",
        "GCP",
        "Amazon Web Services",
        "Microsoft Azure\nLearn",
        "Sketch, InVision",
        "SQL",
        "IoT",
        "IoT",
        "Bachelor of Computer Science",
        "IoT",
        "JavaScript",
        "Develop",
        "DeepLearning",
        "AI",
        "counselor](mailto:degrees-enrollment@coursera.org",
        "the University of Illinois",
        "COVID-19",
        "US Bureau",
        "Computer and Information Technology Occupations](https://www.bls.gov"
      ],
      "CARDINAL": [
        "1](https://www.bls.gov",
        "ten",
        "5",
        "10",
        "5",
        "10",
        "10"
      ],
      "FAC": [
        "the Fourth Industrial Revolution"
      ],
      "GPE": [
        "AI",
        "AI",
        "AI",
        "AI",
        "C++",
        "C++",
        "Cisco",
        "AI"
      ],
      "PERSON": [
        "Java",
        "Java",
        "Cloud Platform",
        "Java",
        "Generative AI",
        "Coursera",
        "Coursera",
        "https://www.bls.gov/ooh/computer-and-information-technology/home.htm"
      ],
      "ORDINAL": [
        "first"
      ]
    },
    "key_phrases": [
      "computer science",
      "job",
      "job requirements",
      "bachelor",
      "degree",
      "data",
      "industry",
      "titles",
      "Common",
      "Cloud"
    ]
  }
}