{
  "url": "https://au.jooble.org/jobs-computer-science-graduate/Sydney-CBD",
  "title": "Urgent! Computer science graduate jobs in Sydney CBD - November 2024 - 542 current vacancies - Jooble",
  "extracted_data": {
    "title": "Urgent! Computer science graduate jobs in Sydney CBD - November 2024 - 542 current vacancies - Jooble",
    "main_content": "$13 per hour\n...teams to drive data-informed decision-making. Qualifications Bachelor's degree or higher in a relevant field such as Computer Science, Mathematics, Statistics, or Information Management 1+ years of experience working in data analysis, reporting, and visualization...Part timeRemote job- ...Need to Succeed: - High level of integrity. - Proficiency in computer skills. - Excellent verbal and written communication skills. -... ...experience is required. - Not suitable for students or recent graduates. - By applying for this role, you agree to receive communications...For graduatesRemote jobFlexible hours\n- ...exciting journey. We are looking for a talented and motivated Graduate Software Engineer to join our high-performing tech team. As a... ...within the team Requirements: Bachelor's degree in Computer Science, Software Engineering, or a related field Knowledge of one...For graduatesFull timeWork at office\n- ...and equip you with practical skills to jumpstart your career in computer engineering. Reasponsibilties: Participate in the testing... ...Currently pursuing a Bachelor's or Master's degree in Computer Science, Software Engineering, or a related field Knowledge of software...For graduatesFull timeInternshipWork at office\n- ...sectors. We are currently hiring positions in our Surry Hills studio. We are looking for experienced and enthusiastic architectural graduates with design and management skills as well as a keen eye for design and detail to work on an exciting range of competition-winning...For graduatesFull timeFor contractorsLocal areaFlexible hours\n- ...Greater China regions; ~ Bachelor's degree (or higher degree) in Computer Science, Information Security, Law or related discipline preferred;... ...Technology | Expected Travel: 0 - 10% | Career Status: Graduate | Employment Type: Regular Full Time | Additional Locations: #LI...For graduatesPermanent employmentFull timeContract workOnlineLocal areaWorldwideHybrid workFlexible hours\n- ...relationship and quality management. Qualifications: - Bachelor's degree in a relevant field or equivalent experience (preferably in Computer Science, Data Science, Statistics, Business Analytics, or a related field). A master's degree is preferred. Experience: - 8 or more...For graduatesPermanent employmentFlexible hours\n- ...explore and refactor legacy applications with uplifting technologies Required skills and qualifications ~ Master’s Degree in Computer Science ~5+ years’ in Agile Software Development ~ Experience with integrating systems 3 + years Beneficial skills and...For graduatesFull timePart time\n- Call: 0450 901 035 West Sector: Technology Job Summary Join this certified 'Great Place to Work' business. Spearhead a Data Transformation initiative. Western Sydney Location - Defined WFH Policy. Job Description About Your New Employer: West Technology...Hybrid work\n- ...applicants. Please see our Reconciliation Action Plan for more information. Minimum qualifications: ~ Bachelor’s degree in Computer Science, a related field, or equivalent practical experience. ~8 years of experience with data structures or algorithms. ~5 years...For graduatesFull timeOnline\n- ...patient and staff safety · Supervise, direct and guide new graduate and student nurses to deliver patient care Sydney Southwest... ...Works well independently and within a team · Basic computer skills Applications close: 5th December 2024 For further enquiries...For graduatesCasual workWork at officeOnline\n- ...Qualifications: ABOUT YOU Successful candidates will preferably possess the following: Degree: B.S. Computer Science or related field We will consider recent Honour Graduates with strong academic results Background or experience in Software Engineering and/or...For graduatesFull timeLocal areaWorldwideWorking Monday to Friday\n- ...appropriate machine learning-led models and effective management of data science projects Keeping abreast of latest developments of data science... ..., or Bachelor’s degree or higher in Statistics, Mathematics, Computer Science, Engineering or Science discipline Proficiency in...Casual workWork at officeRemote jobFlexible hours\n- At ShopGrok, data is at the heart of what we do. Your main responsibilities will be working closely with the Founder, COO and Senior Data Engineers to collect, blend and manage our datasets using SQL and ETL tools, and to build Tableau dashboards that provide retail insights...Full timeWork at officeRemote jobFlexible hours\n- ...applicants. Please see our Reconciliation Action Plan for more information. Minimum qualifications: ~ Bachelor's degree in Computer Science or related technical field, or equivalent practical experience. ~2 years of experience with data structures or algorithms in...For graduatesFull timeImmediate start\n- ...extraction, and model validation using appropriate statistical and computational methods. develop and refine signal processing algorithms to... ...this role, you will have: Honors or master’s degree in data science, with relevant experience in a related field, or degree in a...For graduatesPermanent employmentFull timeTemporary workFixed term contractWork at officeSunday\n- ...is Snowflake for data storage, Snow Park for pipeline build and compute, SnowPark/ notebook/ Data Robot for model builds and Data Robot... ...deployment. Our client is looking for someone to work in their Data Science team and focus on two primary streams: first, building models in...Full timeHybrid workFlexible hours\n- ...(Healthcare & Medical) Accelerate your career while enriching the lives of aged care residents in our supportive Registered Nurse Graduate program with a specialist module in acute care. Now hiring in Maroubra, we are looking for passionate, newly graduated nurses looking...For graduatesFull timeOnlineOverseas\n- ...expert EDUCATION AND QUALIFICATIONS / SKILLS AND COMPETENCIES · Master’s or Bachelor's degree in Business Administration, Computer Science, Information Management, or related fields PERSONAL SKILLS AND REQUIREMENTS · Experience in SAP BTP solutions like SAP...For graduatesPermanent employmentFull timeWorldwideHybrid workFlexible hours\n- ...industry trends, continuously enhancing technical skills and knowledge. Minimum Requirements: ~ Bachelor's or Master's degree in Computer Science, Engineering, or a related field. ~10+ years of progressive experience in IT development roles. ~ Strong proficiency in...For graduatesHybrid work\nSearch Results",
    "summary": "and equip you with practical skills to jumpstart your career inengineering.\nReasponsibilties: Participate in the testingCurrently pursuing a Bachelor's or Master's degree in ComputerSoftware Engineering, or a related field Knowledge of software",
    "keywords": [
      "masters",
      "graduate",
      "science",
      "participate",
      "reasponsibilties",
      "testingcurrently",
      "cbd",
      "practical",
      "urgent",
      "related",
      "jobs",
      "sydney",
      "pursuing",
      "software",
      "computer",
      "skills",
      "knowledge"
    ],
    "prices": [
      {
        "amount": 13.0,
        "currency": "$"
      },
      {
        "amount": 13.0,
        "currency": "$"
      },
      {
        "amount": 104.0,
        "currency": "$"
      },
      {
        "amount": 113.0,
        "currency": "$"
      },
      {
        "amount": 185.0,
        "currency": "$"
      }
    ],
    "dates": [
      "2024-10-25T00:00:00",
      "2024-07-10T00:00:00",
      "2024-11-01T00:00:00",
      "2024-11-01T00:00:00",
      "2024-11-06T00:00:00",
      "2024-11-06T00:00:00",
      "2024-11-15T00:00:00",
      "2024-10-28T00:00:00",
      "2024-11-15T00:00:00",
      "2024-11-06T00:00:00",
      "2024-11-06T00:00:00",
      "2024-11-01T00:00:00",
      "2024-07-15T00:00:00",
      "2024-10-03T00:00:00",
      "2024-11-12T00:00:00",
      "2024-11-16T00:00:00",
      "2024-09-28T00:00:00",
      "2024-11-13T00:00:00",
      "2024-11-15T00:00:00",
      "2024-11-15T00:00:00",
      "2023-04-05T00:00:00",
      "2023-04-10T00:00:00",
      "2023-04-05T00:00:00",
      "2023-04-05T00:00:00",
      "2023-04-10T00:00:00",
      "2023-04-05T00:00:00",
      "2023-04-05T00:00:00",
      "2023-04-10T00:00:00",
      "2023-04-05T00:00:00"
    ],
    "named_entities": {
      "MONEY": [
        "13"
      ],
      "ORG": [
        "Computer Science, Mathematics, Statistics",
        "Graduate Software Engineer",
        "Computer Science, Software Engineering",
        "Bachelor",
        "Computer Science, Software Engineering",
        "Bachelor",
        "Computer Science, Information Security",
        "Computer Science, Data Science, Statistics,",
        "Business Analytics",
        "Computer Science",
        "B.S. Computer Science",
        "Software Engineering",
        "Bachelor",
        "Statistics, Mathematics, Computer Science, Engineering",
        "COO",
        "Senior Data Engineers",
        "SQL",
        "ETL",
        "Bachelor",
        "Computer Science",
        "Data Robot",
        "Data Robot",
        "Data Science",
        "Healthcare & Medical",
        "Registered Nurse Graduate",
        "Bachelor",
        "Business Administration",
        "Computer Science, Information Management",
        "SAP",
        "Computer Science, Engineering"
      ],
      "PRODUCT": [
        "Information Management",
        "Founder"
      ],
      "DATE": [
        "1+ years",
        "~5+ years",
        "3 + years",
        "0450",
        "years",
        "~5 years",
        "December 2024",
        "Monday",
        "Friday",
        "+ years"
      ],
      "PERSON": [
        "Requirements",
        "Knowledge",
        "Knowledge",
        "Law",
        "Career Status",
        "LI",
        "Sydney Southwest",
        "Background",
        "Casual"
      ],
      "NORP": [
        "jumpstart"
      ],
      "GPE": [
        "Surry Hills",
        "China",
        "Tableau",
        "Maroubra"
      ],
      "TIME": [
        "hours",
        "hours",
        "jobFlexible hours",
        "jobFlexible hours",
        "hours",
        "hours"
      ],
      "PERCENT": [
        "0 - 10%"
      ],
      "CARDINAL": [
        "901",
        "ShopGrok",
        "two"
      ],
      "ORDINAL": [
        "5th",
        "first"
      ],
      "FAC": [
        "Snow Park"
      ]
    },
    "key_phrases": [
      "Computer Science",
      "Bachelor degree",
      "data",
      "related",
      "skills",
      "Software Engineering",
      "hours",
      "Qualifications",
      "Management",
      "Basic computer"
    ]
  }
}