{
  "url": "https://www.huzzle.app/blog/best-career-paths-for-computer-science-graduates",
  "title": "Best Career Paths for Computer Science Graduates | Huzzle",
  "extracted_data": {
    "title": "Best Career Paths for Computer Science Graduates | Huzzle",
    "main_content": "Are you a computer science graduate looking to kickstart your career? With the ever-growing demand for tech professionals, the opportunities are endless. In this article, we will explore the best career paths for computer science graduates in the UK. From understanding the field to exploring different paths and preparing for a successful career, we've got you covered.\nBefore diving into the various career options, it's essential to have a clear understanding of the field of computer science. Over the years, computer science has evolved significantly, shaping the way we live and work. From its early days of punch cards and mainframes to today's powerful computers and advanced algorithms, the field has come a long way.\nComputer science is not just about [coding and programming](https://huzzle.app/jobs/graduate-software-engineer-0b03b1ff-cbf3-413f-aa05-8abfd273030d). It encompasses a wide range of topics and disciplines that contribute to the [development and advancement of technology](https://huzzle.app/jobs/graduate-digital-signalling-engineer). It involves the study of algorithms, data structures, software engineering, artificial intelligence, computer graphics, and much more.\nAs a computer science graduate, you possess a unique set of skills that are highly sought after by employers. These skills include problem-solving, critical thinking, and the ability to [analyze complex data](https://huzzle.app/jobs/graduate-junior-software-developer-manchester). With technology becoming increasingly intertwined with every industry, your expertise is crucial in [driving innovation and solving real-world challenges](https://huzzle.app/jobs/graduate-software-developer-london).\nComputer science is a field that is [constantly evolving and adapting](https://huzzle.app/jobs/tech-programme-fe8b889a-cc74-47a8-a60b-c541d30b6261) to new technologies and trends. It is a dynamic and ever-changing field, which means that as a computer science professional, you need to stay updated with the latest advancements and continuously learn and grow.\nThe field has witnessed remarkable advancements, giving rise to new career opportunities. From a focus on hardware and software development, computer science has expanded into specialized areas such as data science, cybersecurity, and artificial intelligence.\nData science, for example, involves [extracting insights and knowledge from vast amounts of data](https://huzzle.app/jobs/graduate-software-engineer-969328). It combines elements of computer science, statistics, and mathematics to analyze and interpret data to make informed decisions. With the increasing availability of data in today's digital age, data science has become a crucial field in various industries, including finance, healthcare, and marketing.\nCybersecurity is another rapidly growing field within computer science. With the rise of cyber threats and attacks, organizations are in constant need of professionals who can [protect their systems and data from malicious activities](https://huzzle.app/jobs/cybersecurity-analyst). Cybersecurity professionals develop strategies and implement measures to safeguard networks, systems, and information from unauthorized access and potential breaches.\nArtificial intelligence (AI) is yet another exciting area within computer science. It involves [creating intelligent machines](https://huzzle.app/jobs/software-engineering-graduate-programme-leeds-875613d3-6f45-4405-84a4-aa162ec64c89) that can perform tasks that typically require human intelligence, such as speech recognition, decision-making, and problem-solving. AI has applications in various fields, including healthcare, finance, and transportation, and has the potential to revolutionize the way we live and work.\nWhile technical skills are fundamental for computer science graduates, employers also value other skills such as [teamwork, communication, and adaptability](https://huzzle.app/jobs/developer-analyst-explorer-graduate-programme-2022-glasgow). The ability to work effectively in a team, communicate complex ideas, and embrace new technologies is highly valued in today's job market.\nTeamwork is essential in computer science as many projects require collaboration with colleagues and professionals from different disciplines. Being able to work well in a team, communicate effectively, and contribute your expertise is crucial for successful project outcomes.\nCommunication skills are equally important. As a computer science professional, you will often need to [explain complex concepts and ideas to non-technical stakeholders](https://huzzle.app/jobs/software-development-graduate-50ed2a3c-2b1a-470f-9b6a-d70fef4627df). Being able to convey information clearly and concisely is essential for effective collaboration and project management.\nAdaptability is a key skill in the ever-changing field of computer science. New technologies and programming languages emerge regularly, and being able to quickly learn and adapt to these changes is crucial for staying relevant and competitive in the job market.\nIn conclusion, computer science is a field that continues to shape our world and offers a wide range of exciting career opportunities. With its evolution and expansion into specialized areas, computer science graduates are well-equipped to tackle the challenges of the digital age and drive innovation in various industries.\nNow that you have a solid understanding of the computer science field, let's explore the different career paths available to you. These career paths offer exciting opportunities for growth and personal development.\nWhen it comes to choosing a career in computer science, the options are vast and diverse. From software development to data science, cybersecurity to artificial intelligence and machine learning, each path offers its own unique challenges and rewards. Let's take a closer look at each of these career paths and discover what they have to offer.\nSoftware development is perhaps the most well-known and sought-after career path for computer science graduates. It involves designing, coding, and testing software applications that meet specific user needs. In this role, you'll work closely with clients and team members to develop innovative solutions and bring ideas to life.\nAs a software developer, you'll have the opportunity to work on a wide range of projects, from mobile apps to web applications, and everything in between. You'll use your problem-solving skills to analyze user requirements and translate them into functional code. With the ever-evolving technology landscape, there will always be new challenges to tackle and skills to learn.\nData science is another booming field that presents great career prospects for computer science graduates. As a data scientist, you'll work with large datasets to extract meaningful insights and make data-driven decisions. Your expertise will be in high demand as organizations strive to leverage data to gain a competitive edge.\nIn this role, you'll use statistical analysis and machine learning techniques to uncover patterns and trends in data. You'll develop algorithms and models that can predict future outcomes and help businesses make informed decisions. From analyzing customer behavior to optimizing supply chain operations, data science offers endless possibilities for innovation and impact.\nIn an increasingly digital world, cybersecurity has become a top priority for organizations. As a cybersecurity professional, you'll protect sensitive information and systems from cyber threats. Your role will involve implementing robust security measures, conducting risk assessments, and responding to security incidents.\nWith the rise in cybercrime and data breaches, the demand for cybersecurity professionals is at an all-time high. As a cybersecurity expert, you'll be at the forefront of defending against hackers and ensuring the integrity of digital infrastructure. From developing secure networks to conducting penetration testing, your work will play a crucial role in safeguarding organizations and individuals from cyber threats.\nArtificial intelligence (AI) and machine learning (ML) are revolutionizing various industries. As an AI/ML engineer, you'll develop algorithms and models that enable machines to learn and make intelligent decisions. From self-driving cars to personalized healthcare, your work will shape the technologies of the future.\nIn this role, you'll work with large datasets and complex algorithms to train machines to recognize patterns, make predictions, and automate tasks. You'll collaborate with interdisciplinary teams to develop cutting-edge AI solutions that have the potential to transform industries and improve people's lives. With AI and ML being at the forefront of technological advancements, this career path offers endless opportunities for innovation and exploration.\nAs you can see, the world of computer science offers a multitude of career paths, each with its own set of challenges and opportunities. Whether you choose software development, data science, cybersecurity, or AI/ML engineering, you'll be embarking on a rewarding journey filled with continuous learning and growth. So, take the time to explore these different paths, identify your passions and strengths, and make an informed decision that aligns with your goals and aspirations.\nSpecializations play a key role in computer science careers, allowing you to delve deeper into specific areas of interest. Let's explore the importance of specializations and the popular specializations with promising career prospects.\nSpecializations enable you to develop specialized expertise that sets you apart from other professionals. They provide a focused learning experience and demonstrate your commitment to a particular field. Employers often value candidates with specialized knowledge, as it showcases a deep understanding and passion for a specific area.\nWhen you specialize in a particular field, you have the opportunity to gain in-depth knowledge and skills that are highly sought after in the industry. For example, if you choose to specialize in software engineering, you can become proficient in programming languages like Java, Python, or C++. You can also gain expertise in software development methodologies, such as Agile or Scrum, which are widely used in the industry.\nSpecializations also allow you to explore the latest advancements and trends in your chosen field. By staying up-to-date with emerging technologies and industry best practices, you can position yourself as a valuable asset to employers. For instance, if you specialize in artificial intelligence, you can stay informed about breakthroughs in machine learning algorithms, neural networks, and natural language processing techniques.\nIn the UK job market, some of the popular specializations include software engineering, data analytics, cybersecurity, and artificial intelligence. Let's take a closer look at these specializations and the career prospects they offer.\nSoftware engineering offers a wide range of opportunities, with roles such as front-end developer, backend developer, and full-stack developer. As a software engineer, you can work on developing web applications, mobile apps, or even embedded systems. With the increasing demand for software solutions across industries, software engineers are in high demand.\nData analytics provides opportunities in data visualization, business intelligence, and data engineering. As a data analyst, you can analyze large datasets to uncover insights and make data-driven decisions. Data engineers, on the other hand, focus on building and maintaining data infrastructure to support analytics initiatives. With the exponential growth of data in today's digital age, data analytics specialists are in high demand.\nCybersecurity specialists are in high demand, with various roles available, including security analyst, ethical hacker, and incident responder. As organizations face increasing cyber threats, cybersecurity professionals play a crucial role in protecting sensitive information and ensuring the security of computer systems. With the rise of remote work and the increasing reliance on technology, the demand for cybersecurity specialists is expected to continue growing.\nArtificial intelligence specialists can explore roles such as AI researcher, machine learning engineer, and natural language processing specialist. With advancements in AI technologies, organizations are leveraging AI to automate processes, improve decision-making, and enhance customer experiences. As an AI specialist, you can contribute to cutting-edge research and development in areas like computer vision, robotics, and autonomous systems.\nOverall, specializations in computer science offer exciting career prospects and the opportunity to make a significant impact in your chosen field. By choosing a specialization that aligns with your interests and career goals, you can carve out a successful and fulfilling career in the dynamic and ever-evolving field of computer science.\nNow that you have a clearer idea of the career paths and specializations, it's essential to prepare yourself for a successful career in computer science. Let's explore the key aspects of preparation.\nWhile having a degree in computer science is a great start, continuous learning is crucial in this rapidly evolving field. Consider pursuing advanced degrees or certifications to enhance your knowledge and stay up-to-date with the latest technologies and industry trends. Attending career events, job fairs, and networking events can also provide valuable insights into the job market and help you make informed decisions about your career path.\nFurthermore, it's important to take advantage of the resources available to you. Many universities and online platforms offer free or low-cost courses and tutorials on various computer science topics. These resources can help you deepen your understanding of specific areas and develop new skills.\nInternships and work placements provide valuable hands-on experience and help you develop practical skills. Seek out opportunities to work on real-world projects and gain exposure to different aspects of the industry. Consider contributing to open-source projects or building your own portfolio to showcase your abilities to potential employers.\nIn addition to internships, participating in hackathons and coding competitions can also be a great way to gain experience and demonstrate your problem-solving abilities. These events often bring together talented individuals from various backgrounds, allowing you to learn from others and expand your professional network.\nNetworking is essential in any career, and computer science is no exception. Attend networking events, join professional organizations, and connect with industry experts and fellow professionals. Engage in online communities and forums to stay updated with the latest trends and exchange knowledge with like-minded individuals.\nMoreover, consider seeking out mentors who can provide guidance and support as you navigate your career in computer science. Mentors can offer valuable insights, share their experiences, and help you make informed decisions about your professional development.\nLastly, don't underestimate the power of continuous learning and professional development. Attend conferences, workshops, and webinars to expand your knowledge and stay up-to-date with the latest advancements in the field. Additionally, consider pursuing certifications in specialized areas of computer science to demonstrate your expertise and increase your marketability.\nThe field of computer science is constantly evolving, driven by emerging technologies and changing demands. Let's take a look at some of the future trends that will shape computer science careers.\nEmerging technologies such as quantum computing, blockchain, and Internet of Things (IoT) are set to disrupt various industries. Quantum computing, with its immense computational power, has the potential to revolutionize fields such as cryptography and drug discovery. Imagine a world where complex problems that currently take years to solve can be cracked in a matter of minutes. This breakthrough could lead to groundbreaking advancements in fields like medical research and climate modeling.\nBlockchain, on the other hand, is transforming the way we conduct transactions. Its decentralized nature ensures transparency, security, and immutability. This technology has the potential to revolutionize industries such as finance and supply chain management. Imagine a future where every transaction is recorded on a tamper-proof digital ledger, eliminating the need for intermediaries and reducing the risk of fraud.\nThe Internet of Things is creating a network of interconnected devices, revolutionizing areas such as healthcare, transportation, and smart cities. Imagine a world where your refrigerator can automatically order groceries when it detects that you're running low, or where traffic lights can optimize traffic flow based on real-time data. This interconnectedness has the potential to improve efficiency, convenience, and sustainability in various aspects of our lives.\nThe demand for computer science professionals is expected to continue surging in the UK job market. With the government's emphasis on digital transformation and the growth of tech startups, the job prospects for computer science graduates look promising. Roles in areas such as artificial intelligence, cybersecurity, and data science are projected to see significant growth.\nArtificial intelligence (AI) is becoming increasingly integrated into our daily lives. From virtual assistants like Siri and Alexa to self-driving cars, AI is transforming the way we interact with technology. As AI continues to advance, the demand for professionals who can develop and optimize AI algorithms will only increase. This presents exciting opportunities for computer science graduates to work on cutting-edge projects that have the potential to shape the future.\nCybersecurity is another area that is expected to see significant growth. With the increasing reliance on technology and the rise in cyber threats, organizations are investing heavily in protecting their systems and data. Computer science professionals with expertise in cybersecurity will be in high demand to develop robust security measures and defend against cyber attacks.\nData science is also a field that is predicted to experience substantial growth. As more and more data is generated, organizations are looking for ways to extract valuable insights from this wealth of information. Data scientists play a crucial role in analyzing and interpreting data to drive informed decision-making. With the increasing importance of data-driven strategies, the demand for skilled data scientists is expected to soar.\nAs a computer science graduate, you have an exciting journey ahead. By understanding the field, exploring different career paths, specializing in key areas, and preparing for success, you'll be well-equipped to navigate the job market and embark on a rewarding career in the dynamic world of computer science. So, seize the opportunities, keep learning, and embrace the exciting challenges that await you!",
    "authors": [
      "Charlie Mart",
      "Founders Associate",
      "Author",
      "Aspiring Business Leader Driven To Change The World Through Tech",
      "The Late Steve Jobs Once Said 'The Only Way To Do Great Work Is To Love What You Do'. Following These Wise Words",
      "I Am Currently Focused On Growing Huzzle So Every Student Can Find Their Dream Graduate Job"
    ],
    "summary": "In this article, we will explore the best career paths for computer science graduates in the UK.\nUnderstanding the Computer Science FieldBefore diving into the various career options, it's essential to have a clear understanding of the field of computer science.\nKey Skills for Computer Science GraduatesWhile technical skills are fundamental for computer science graduates, employers also value other skills such as teamwork, communication, and adaptability.\nThe Role of Specializations in Computer Science CareersSpecializations play a key role in computer science careers, allowing you to delve deeper into specific areas of interest.\nFuture Trends in Computer Science CareersThe field of computer science is constantly evolving, driven by emerging technologies and changing demands.",
    "keywords": [
      "cybersecurity",
      "work",
      "science",
      "paths",
      "field",
      "graduates",
      "data",
      "youll",
      "ai",
      "software",
      "computer",
      "career",
      "best"
    ],
    "named_entities": {
      "GPE": [
        "UK",
        "london",
        "AI",
        "AI",
        "UK",
        "AI",
        "AI",
        "AI",
        "UK",
        "AI",
        "AI"
      ],
      "DATE": [
        "the years",
        "early days",
        "today",
        "today",
        "today",
        "today",
        "years"
      ],
      "ORG": [
        "AI",
        "Software",
        "ML",
        "AI/ML",
        "ML",
        "AI/ML",
        "Software",
        "AI",
        "IoT",
        "Quantum",
        "Alexa",
        "AI"
      ],
      "PERSON": [
        "Java",
        "C++",
        "Specializations",
        "mobile apps",
        "Internships",
        "Blockchain",
        "Siri"
      ],
      "NORP": [
        "Agile"
      ],
      "PRODUCT": [
        "Scrum"
      ]
    },
    "key_phrases": [
      "computer science",
      "data",
      "career",
      "science graduates",
      "field",
      "work",
      "software",
      "artificial intelligence",
      "professionals",
      "opportunities"
    ]
  }
}